Workbook

Sheet Lisez-moi
A1: Carthago FinTech — Liste des écarts (étape 1)
A2: Étude de cas ISO/IEC 27001 Lead Implementer — document pédagogique, organisation fictive (v1.0, sept. 2026)
A4: Objectif | B4: Recenser les points faibles décrits dans le cas, avec leur source, afin d'alimenter ensuite l'analyse de risques, le plan de traitement et la déclaration d'applicabilité (SoA).
A5: Onglets | B5: Écarts : la liste principale (45 lignes) · Synthèse : comptages automatiques · Chronologie : l'incident du 3 sept. 2026 relié aux écarts.
A6: Cellules à modifier | B6: Colonnes à en-tête doré de l'onglet Écarts : Criticité proposée, Risque associé, Statut, Notes. Les cellules de ces colonnes sont en jaune clair (sauf Criticité, colorée selon sa valeur). Les autres colonnes décrivent le constat et peuvent être ajustées si besoin.
A7: Exemple de saisie | B7: Risque associé : R-03 · Statut : Confirmé · Notes : « Vérifier l'export des rôles Azure avec le CISO ».
A8: Colonne « Nature » | B8: Fait du cas = indiqué explicitement dans le document · Déduit = conclusion tirée du cas, à valider · À clarifier = information insuffisante, à confirmer lors des ateliers.
A9: Hypothèses et limites | B9: 1) Tous les constats viennent uniquement du document du cas (v1.0) ; les numéros de section et de page renvoient à ce document. 2) La chronologie de l'incident et le délai d'environ 1 h (SOC-03) sont lus sur la Figure 4 : à revérifier sur le document. 3) Les contrôles de l'Annexe A ont été recoupés avec le texte de la norme ISO/IEC 27001:2022 ; le lien entre un écart et une clause ou un contrôle reste indicatif et doit être justifié dans votre analyse (ISO/IEC 27002:2022 donne le détail de chaque contrôle). 4) La criticité est une proposition de départ, à réévaluer avec votre propre méthode d'appréciation des risques. 5) Aucune preuve n'est encore disponible : la colonne « Preuve à demander » liste ce qu'il faudrait obtenir lors des ateliers.
A10: Étape suivante | B10: Regrouper ces écarts en risques (registre des risques), puis relier chaque risque à un traitement et à un contrôle de l'Annexe A pour la SoA.
A12: Légende des couleurs
A13: En-tête doré | B13: Colonne à compléter ou à ajuster
A14: Cellule jaune clair | B14: Cellule de saisie (risque associé, statut, notes)
A15: Haute / Moyenne / Faible | B15: Criticité proposée : Haute (rouge pâle), Moyenne (jaune), Faible (vert)

Sheet Écarts
A1: Liste des écarts — Carthago FinTech
A2: Source : étude de cas v1.0 (sept. 2026). Colonnes à en-tête doré = à compléter. Filtres actifs sur la ligne d'en-tête.
A4: ID | B4: Domaine | C4: Constat (écart observé) | D4: Source dans le cas | E4: Nature | F4: Exigence ISO 27001:2022 (clause, indicatif) | G4: Contrôle(s) Annexe A (indicatif) | H4: Lié à l'incident du 3 sept. ? | I4: Criticité proposée | J4: Preuve à demander | K4: Risque associé (ID) | L4: Statut | M4: Notes personnelles
A5: GOV-01 | B5: Gouvernance & pilotage | C5: Les responsabilités relatives au SMSI n'ont jamais été formalisées de manière exhaustive ; certaines décisions de sécurité reposent sur des relations informelles entre CTO, CIO et CISO. | D5: §3, p.6 | E5: Fait du cas | F5: 5.3 ; 5.1 | G5: A.5.2 ; A.5.4 | H5: Non | I5: Haute | J5: Matrice RACI ou fiches de rôle, exemples de décisions sans propriétaire clair | L5: À analyser
A6: GOV-02 | B6: Gouvernance & pilotage | C6: Le comité Cyber & Risques se réunit « en principe » tous les deux mois ; des comptes rendus existent mais le suivi des décisions n'est pas centralisé. | D6: §3, p.6 | E6: Fait du cas | F6: 5.1 ; 9.3 ; 10.2 | G6: A.5.4 | H6: Non | I6: Moyenne | J6: Comptes rendus des 12 derniers mois, registre des décisions et actions, fréquence réelle des réunions | L6: À analyser
A7: GOV-03 | B7: Gouvernance & pilotage | C7: Conformité, protection des données et gestion des fournisseurs sont répartis entre CISO, Risques & Conformité, DPO et juridique, sans propriétaire unique identifié. | D7: §3, p.6 | E7: Déduit | F7: 5.3 | G7: A.5.2 ; A.5.31 | H7: Non | I7: Moyenne | J7: Répartition des responsabilités par thème (RACI) | L7: À analyser
A8: GOV-04 | B8: Gouvernance & pilotage | C8: Plusieurs actions décidées lors de l'exercice de crise de novembre 2025 ont un suivi dispersé. | D8: §12, p.16 | E8: Fait du cas | F8: 9.3 ; 10.2 | G8: A.5.27 | H8: Non | I8: Moyenne | J8: Plan d'actions issu de l'exercice, état de clôture de chaque action | L8: À analyser
A9: GOV-05 | B9: Gouvernance & pilotage | C9: Peu d'indicateurs relient la performance du SMSI aux objectifs métier ; les KPI disponibles sont surtout techniques. | D9: §12, p.16 | E9: Fait du cas | F9: 6.2 ; 9.1 | G9: — | H9: Non | I9: Moyenne | J9: Liste des KPI actuels, objectifs de sécurité, tableaux de bord présentés à la Direction | L9: À analyser
A10: GOV-06 | B10: Gouvernance & pilotage | C10: Les politiques existent (sécurité, classification, usage acceptable, incidents, accès) mais seules certaines ont été mises à jour en 2025 : cycle de revue et d'approbation non démontré. | D10: §12, p.16 | E10: Déduit | F10: 5.2 ; 7.5 | G10: A.5.1 | H10: Non | I10: Faible | J10: Dates de version et d'approbation, historique des revues de chaque politique | L10: À analyser
A11: ACT-01 | B11: Actifs & classification | C11: L'inventaire des actifs informationnels n'est pas consolidé à l'échelle de l'entreprise ; la CMDB technique est partielle. | D11: §12, p.16 | E11: Fait du cas | F11: 6.1.2 | G11: A.5.9 | H11: Non | I11: Haute | J11: Extrait de la CMDB, liste des actifs informationnels, propriétaires d'actifs | L11: À analyser
A12: ACT-02 | B12: Actifs & classification | C12: La politique de classification à quatre niveaux (2025) n'est pas appliquée uniformément, notamment pour les exports de reporting et les documents partagés avec les partenaires. | D12: §5, p.9 | E12: Fait du cas | F12: 7.5 ; 8.1 | G12: A.5.12 ; A.5.13 ; A.5.14 | H12: Non | I12: Moyenne | J12: Échantillon d'exports et de documents partenaires : présence du marquage de classification | L12: À analyser
A13: IAM-01 | B13: IAM (identités & accès) | C13: Lors des changements de fonction, l'ajout de nouveaux droits est correct, mais le retrait des droits historiques dépend souvent d'une action manuelle. | D13: §6, p.10 | E13: Fait du cas | F13: 8.1 | G13: A.5.16 ; A.5.18 | H13: Oui | I13: Haute | J13: Procédure Mover, tickets de mobilité, comparaison des droits avant/après sur un échantillon | L13: À analyser
A14: IAM-02 | B14: IAM (identités & accès) | C14: Revues d'accès semestrielles sur quelques systèmes critiques, annuelles ou ponctuelles sur les autres ; la revue n'avait pas détecté le rôle Azure hérité du compte compromis. | D14: §6, p.10 ; §13, p.17 | E14: Fait du cas | F14: 8.1 ; 9.1 | G14: A.5.18 | H14: Oui | I14: Haute | J14: Calendrier et comptes rendus des revues d'accès, périmètre couvert, écarts relevés | L14: À analyser
A15: IAM-03 | B15: IAM (identités & accès) | C15: Accumulation de droits historiques sur quelques comptes Azure ; certains administrateurs conservent des rôles transverses entre environnements pour les interventions d'urgence. | D15: §6, p.10 ; §4, p.7 | E15: Fait du cas | F15: 8.1 | G15: A.8.2 ; A.5.15 ; A.5.3 | H15: Oui | I15: Haute | J15: Export des rôles RBAC Azure / Entra ID, liste des rôles transverses et de leur justification | L15: À analyser
A16: IAM-04 | B16: IAM (identités & accès) | C16: Le PAM (gestion des accès privilégiés) n'est qu'en phase pilote ; les comptes d'administration séparés ne couvrent que la plupart des équipes. | D16: §6, p.10 | E16: Fait du cas | F16: 8.1 | G16: A.8.2 | H16: Oui | I16: Haute | J16: Périmètre du pilote PAM, liste des comptes d'administration et des comptes nominatifs | L16: À analyser
... A49: PIL-02 | B49: Audit & amélioration continue | C49: Aucune méthodologie formalisée d'appréciation des risques ni registre de risques consolidé n'est mentionné ; la Direction demande de démontrer que les risques sont maîtrisés. | D49: §13, p.17 ; §12, p.16 | E49: Déduit | F49: 6.1.2 ; 6.1.3 | G49: — | H49: Non | I49: Haute | J49: Méthode et registre de risques existants, critères d'acceptation | L49: À analyser

Sheet Synthèse
A1: Synthèse des écarts
A2: Tous les chiffres se recalculent à partir de l'onglet Écarts (lignes 5 à 200).
A4: 1. Par domaine
A5: Domaine | B5: Nombre d'écarts | C5: dont criticité Haute | D5: dont liés à l'incident
A6: Gouvernance & pilotage | B6: =COUNTIF(Écarts!$B$5:$B$200,A6) -> 6 | C6: =COUNTIFS(Écarts!$B$5:$B$200,A6,Écarts!$I$5:$I$200,"Haute") -> 1 | D6: =COUNTIFS(Écarts!$B$5:$B$200,A6,Écarts!$H$5:$H$200,"Oui") -> 0
A7: Actifs & classification | B7: =COUNTIF(Écarts!$B$5:$B$200,A7) -> 2 | C7: =COUNTIFS(Écarts!$B$5:$B$200,A7,Écarts!$I$5:$I$200,"Haute") -> 1 | D7: =COUNTIFS(Écarts!$B$5:$B$200,A7,Écarts!$H$5:$H$200,"Oui") -> 0
A8: IAM (identités & accès) | B8: =COUNTIF(Écarts!$B$5:$B$200,A8) -> 9 | C8: =COUNTIFS(Écarts!$B$5:$B$200,A8,Écarts!$I$5:$I$200,"Haute") -> 5 | D8: =COUNTIFS(Écarts!$B$5:$B$200,A8,Écarts!$H$5:$H$200,"Oui") -> 7
A9: Cloud & infrastructure | B9: =COUNTIF(Écarts!$B$5:$B$200,A9) -> 4 | C9: =COUNTIFS(Écarts!$B$5:$B$200,A9,Écarts!$I$5:$I$200,"Haute") -> 0 | D9: =COUNTIFS(Écarts!$B$5:$B$200,A9,Écarts!$H$5:$H$200,"Oui") -> 0
A10: DevSecOps | B10: =COUNTIF(Écarts!$B$5:$B$200,A10) -> 4 | C10: =COUNTIFS(Écarts!$B$5:$B$200,A10,Écarts!$I$5:$I$200,"Haute") -> 0 | D10: =COUNTIFS(Écarts!$B$5:$B$200,A10,Écarts!$H$5:$H$200,"Oui") -> 0
A11: SOC & journalisation | B11: =COUNTIF(Écarts!$B$5:$B$200,A11) -> 5 | C11: =COUNTIFS(Écarts!$B$5:$B$200,A11,Écarts!$I$5:$I$200,"Haute") -> 4 | D11: =COUNTIFS(Écarts!$B$5:$B$200,A11,Écarts!$H$5:$H$200,"Oui") -> 4
A12: Continuité & résilience | B12: =COUNTIF(Écarts!$B$5:$B$200,A12) -> 5 | C12: =COUNTIFS(Écarts!$B$5:$B$200,A12,Écarts!$I$5:$I$200,"Haute") -> 1 | D12: =COUNTIFS(Écarts!$B$5:$B$200,A12,Écarts!$H$5:$H$200,"Oui") -> 0
A13: Fournisseurs & tiers | B13: =COUNTIF(Écarts!$B$5:$B$200,A13) -> 4 | C13: =COUNTIFS(Écarts!$B$5:$B$200,A13,Écarts!$I$5:$I$200,"Haute") -> 1 | D13: =COUNTIFS(Écarts!$B$5:$B$200,A13,Écarts!$H$5:$H$200,"Oui") -> 0
A14: Conformité légale | B14: =COUNTIF(Écarts!$B$5:$B$200,A14) -> 3 | C14: =COUNTIFS(Écarts!$B$5:$B$200,A14,Écarts!$I$5:$I$200,"Haute") -> 1 | D14: =COUNTIFS(Écarts!$B$5:$B$200,A14,Écarts!$H$5:$H$200,"Oui") -> 0
A15: Sensibilisation & compétences | B15: =COUNTIF(Écarts!$B$5:$B$200,A15) -> 1 | C15: =COUNTIFS(Écarts!$B$5:$B$200,A15,Écarts!$I$5:$I$200,"Haute") -> 1 | D15: =COUNTIFS(Écarts!$B$5:$B$200,A15,Écarts!$H$5:$H$200,"Oui") -> 1
A16: Audit & amélioration continue | B16: =COUNTIF(Écarts!$B$5:$B$200,A16) -> 2 | C16: =COUNTIFS(Écarts!$B$5:$B$200,A16,Écarts!$I$5:$I$200,"Haute") -> 1 | D16: =COUNTIFS(Écarts!$B$5:$B$200,A16,Écarts!$H$5:$H$200,"Oui") -> 0
A17: Total | B17: =SUM(B6:B16) -> 45 | C17: =SUM(C6:C16) -> 16 | D17: =SUM(D6:D16) -> 12
A18: Contrôle : nombre de lignes dans Écarts | B18: =COUNTA(Écarts!$A$5:$A$200) -> 45 | C18: =IF(B17=B18,"OK","Domaine manquant ou mal orthographié") -> OK
A21: 2. Par criticité proposée
A22: Criticité | B22: Nombre | C22: Part du total
A23: Haute | B23: =COUNTIF(Écarts!$I$5:$I$200,A23) -> 16 | C23: =IFERROR(B23/B$26,0) -> 0.35555556
A24: Moyenne | B24: =COUNTIF(Écarts!$I$5:$I$200,A24) -> 26 | C24: =IFERROR(B24/B$26,0) -> 0.57777778
A25: Faible | B25: =COUNTIF(Écarts!$I$5:$I$200,A25) -> 3 | C25: =IFERROR(B25/B$26,0) -> 0.066666667
A26: Total | B26: =SUM(B23:B25) -> 45 | C26: =SUM(C23:C25) -> 1
A28: 3. Par nature du constat
A29: Nature | B29: Nombre | C29: Part du total
A30: Fait du cas | B30: =COUNTIF(Écarts!$E$5:$E$200,A30) -> 33 | C30: =IFERROR(B30/B$33,0) -> 0.73333333
A31: Déduit | B31: =COUNTIF(Écarts!$E$5:$E$200,A31) -> 9 | C31: =IFERROR(B31/B$33,0) -> 0.2
A32: À clarifier | B32: =COUNTIF(Écarts!$E$5:$E$200,A32) -> 3 | C32: =IFERROR(B32/B$33,0) -> 0.066666667
A33: Total | B33: =SUM(B30:B32) -> 45 | C33: =SUM(C30:C32) -> 1
A35: 4. Par statut
A36: Statut | B36: Nombre | C36: Part du total
A37: À analyser | B37: =COUNTIF(Écarts!$L$5:$L$200,A37) -> 45 | C37: =IFERROR(B37/B$40,0) -> 1
A38: Confirmé | B38: =COUNTIF(Écarts!$L$5:$L$200,A38) -> 0 | C38: =IFERROR(B38/B$40,0) -> 0
A39: Écarté | B39: =COUNTIF(Écarts!$L$5:$L$200,A39) -> 0 | C39: =IFERROR(B39/B$40,0) -> 0
A40: Total | B40: =SUM(B37:B39) -> 45 | C40: =SUM(C37:C39) -> 1

Sheet Chronologie
A1: Incident du 3 septembre 2026 — chronologie reliée aux écarts
A2: Source : §13, p.17 et Figure 4 du cas (heures lues sur la figure : à revérifier). Les IDs renvoient à l'onglet Écarts.
A4: Heure | B4: Événement | C4: Écarts révélés (IDs) | D4: Ce que cela montre
A5: 18:42 | B5: Phishing imitant une notification Microsoft 365 ; l'ingénieur DevOps saisit son mot de passe | C5: HUM-01 | D5: Sensibilisation insuffisante pour les rôles techniques malgré les simulations de phishing
A6: 18:50 | B6: Multiples demandes MFA sur le téléphone de l'ingénieur | C6: IAM-06 ; IAM-05 | D6: Le MFA par notification est exposé à la fatigue MFA ; la méthode utilisée n'est pas précisée
A7: 18:54 | B7: Une demande MFA est approuvée | C7: IAM-06 ; HUM-01 | D7: L'utilisateur a pris les demandes pour une opération de maintenance
A8: 19:06 | B8: Accès au portail Azure avec un rôle privilégié hérité d'un ancien projet | C8: IAM-01 ; IAM-02 ; IAM-03 ; IAM-04 | D8: Mobilité sans retrait des droits, revue d'accès incomplète, privilèges excessifs, PAM seulement en pilote
A9: 19:28 | B9: Alerte tardive dans le SIEM | C9: SOC-01 ; SOC-02 ; IAM-08 | D9: Sources d'identité et d'administration Azure non corrélées de façon homogène
A10: 19:36 | B10: Le MSSP escalade l'incident en P1 | C10: SOC-03 ; SOC-04 | D10: Dépendance au processus d'escalade du MSSP ; annexe contractuelle sur les sources de logs non révisée
A11: 20:05 | B11: Compte bloqué et jetons de session révoqués | C11: SOC-03 | D11: Environ 1 h après l'accès Azure (19:06)
A12: 22:30 | B12: Confinement confirmé ; secrets potentiellement exposés renouvelés | C12: IAM-07 | D12: Les secrets statiques ont dû être renouvelés ; pas de preuve d'exfiltration massive d'après les journaux disponibles
